fastcord/__init__.py
fastcord/fastcord.py
fastcord/command/command.py
fastcord/objects/activity.py
fastcord/objects/attachment.py
fastcord/objects/channel.py
fastcord/objects/embed.py
fastcord/objects/emoji.py
fastcord/objects/guild.py
fastcord/objects/message.py
fastcord/objects/presence.py
fastcord/objects/reaction.py
fastcord/objects/role.py
fastcord/objects/user.py
fastcord/utils/color.py
fastcord/utils/date.py
fastcord/utils/dict.py
fastcord/utils/events.py
fastcord/utils/http.py
fastcord-0.3.1.dist-info/LICENSE
fastcord-0.3.1.dist-info/METADATA
fastcord-0.3.1.dist-info/WHEEL
fastcord-0.3.1.dist-info/top_level.txt
fastcord-0.3.1.dist-info/RECORD
