Metadata-Version: 2.1
Name: fastcord
Version: 0.3.1
Summary: another discord api wrapper for writing bots
Home-page: https://github.com/dskprt/fastcord
Author: dskprt
License: UNKNOWN
Platform: UNKNOWN
Classifier: Development Status :: 4 - Beta
Classifier: License :: OSI Approved :: MIT License
Classifier: Programming Language :: Python :: 3.8
Classifier: Programming Language :: Python :: 3.7
Classifier: Programming Language :: Python :: 3.6
Classifier: Operating System :: OS Independent
Requires-Python: >=3.6
Requires-Dist: websocket-client
